pykawaii/__init__.py
pykawaii/cache.py
pykawaii/client.py
pykawaii/http.py
pykawaii/models/__init__.py
pykawaii/models/nsfw.py
pykawaii/models/sfw.py
pykawaii-4.1.0.dist-info/LICENSE
pykawaii-4.1.0.dist-info/METADATA
pykawaii-4.1.0.dist-info/WHEEL
pykawaii-4.1.0.dist-info/top_level.txt
pykawaii-4.1.0.dist-info/RECORD
