Metadata-Version: 2.1
Name: pykawaii
Version: 4.1.0
Summary: Python api wrapper for the waifu.pics api
Home-page: https://github.com/Okimii/pykawaii
Author: Okimii
License: MIT
Keywords: waifu.pics python api wrapper
License-File: LICENSE
Requires-Dist: aiohttp
Requires-Dist: setuptools
